Metadata-Version: 2.4
Name: pygremlinbox-mpl-2-0
Version: 1.4.0
Summary: Supply chain security testing package with MPL-2.0 licence
Author-email: PyGremlinBox Maintainer <simon@sigre.xyz>
License: MPL-2.0
Project-URL: Homepage, https://github.com/gocortexio/pygremlinbox
Project-URL: Repository, https://github.com/gocortexio/pygremlinbox
Keywords: security,testing,licence,supply-chain
Classifier: Development Status :: 4 - Beta
Classifier: Intended Audience :: Developers
Classifier: License :: OSI Approved :: Mozilla Public License 2.0 (MPL 2.0)
Classifier: Operating System :: OS Independent
Classifier: Programming Language :: Python :: 3
Classifier: Programming Language :: Python :: 3.11
Classifier: Topic :: Security
Classifier: Topic :: Software Development :: Testing
Requires-Python: >=3.11
License-File: LICENCE
Dynamic: license-file
